Workbook

Sheet Financial History
A1: Metric | B1: 2021A | C1: 2022A | D1: 2023A | E1: 2024A | F1: 2025A
A2: Revenue ($M) | B2: 257637 | C2: 282836 | D2: 307394 | E2: 350018 | F2: 402779
A3: Rev Growth | D3: 0.0868 | E3: 0.1387 | F3: 0.1507
A4: COGS ($M) | C4: 126203 | D4: 133452 | E4: 146318 | F4: 162322
A5: Gross Profit ($M) | C5: 156633 | D5: 173942 | E5: 203700 | F5: 240457
A6: Gross Margin | C6: 0.5538 | D6: 0.5658 | E6: 0.5819 | F6: 0.5969
A7: R&D ($M) | C7: 39500 | D7: 45364 | E7: 45427 | F7: 49600
A8: R&D Ratio | C8: 0.1397 | D8: 0.1476 | E8: 0.1298 | F8: 0.1231
A9: SG&A ($M) | C9: 26598 | D9: 24870 | E9: 28400 | F9: 29500
A10: SG&A Ratio | C10: 0.094 | D10: 0.0809 | E10: 0.0811 | F10: 0.0732
A11: EBIT ($M) | C11: 74988 | D11: 84233 | E11: 112230 | F11: 128940
A12: EBIT Margin | C12: 0.2651 | D12: 0.274 | E12: 0.3206 | F12: 0.32
A13: Net Income ($M) | C13: 59972 | D13: 73795 | E13: 100118 | F13: 132190
A14: Net Margin | C14: 0.212 | D14: 0.2401 | E14: 0.286 | F14: 0.3282

Sheet Valuation
A1: Metric
A2: Current Market Cap ($B) | B2: 4692.9
A3: Current Price ($) | B3: 387.35
A4: PE (TTM) | B4: 29.6
A5: PE (Forward) | B5: 26.8
A6: Shares Outstanding (M) | B6: 5824
A7: 52W High ($) | B7: 402
A8: 52W Low ($) | B8: 159.61

Sheet Fiscal Year Info
A1: Fiscal Year → Calendar Year Mapping
A3: FY End Month: | B3: 12
A4: FY End Date: | B4: 12-31
A5: Calendar Year Aligned: | B5: Yes
A7: FY ends in December, aligned with calendar year
A9: Detailed Mappings:
A10: Report Date | B10: FY Label | C10: Natural Year
A13: Full Notes:
A14: Google fiscal year ends December 31, aligned with calendar year. No mapping needed.

Sheet Assumptions
A1: Active Scenario | B1: 2
A2: Metric | C2: Bear | D2: Base | E2: Bull | F2: Active Value | G2: Source / Derivation
A3: --- AIDC CapEx ---
A4: AIDC CapEx Starting ($B) | C4: 3000 | D4: 3000 | E4: 3000 | F4: =INDEX(C4:E4,$B$1) | G4: 基于Gartner 2025全球IT支出预测(~$5T) × 数字化服务渗透率，取$3T作为GOOGL可参与市场
A5: AIDC CapEx CAGR Y1-Y3 | C5: 0.09 | D5: 0.14 | E5: 0.2 | F5: =INDEX(C5:E5,$B$1) | G5: 基于IDC/Gartner对AI和云计算支出的增速预测(15-25%)，Bear取低、Bull取高
A6: AIDC CapEx CAGR Y4-Y6 | C6: 0.06 | D6: 0.1 | E6: 0.14 | F6: =INDEX(C6:E6,$B$1) | G6: 增速衰减假设：参考S曲线，渗透率10%-50%阶段增速自然下降
A7: AIDC CapEx CAGR Y7-Y10 | C7: 0.04 | D7: 0.06 | E7: 0.09 | F7: =INDEX(C7:E7,$B$1) | G7: 长期增速向GDP+通胀回归(3-6%)，参考Cisco/AWS历史增速衰减轨迹
A8: NVDA Addressable Rate | C8: 0.4 | D8: 0.4 | E8: 0.4 | F8: =INDEX(C8:E8,$B$1) | G8: 40%：基于GOOGL业务覆盖（搜索+Cloud+YouTube+Android）占全球数字支出的比例
A9: Starting Share | C9: 0.336 | D9: 0.336 | E9: 0.336 | F9: =INDEX(C9:E9,$B$1) | G9: 33.6%：基于2025A实际收入/$3T SAM计算
A10: Terminal Share | C10: 0.31 | D10: 0.34 | E10: 0.38 | F10: =INDEX(C10:E10,$B$1) | G10: Bear 31%: 搜索被AI蚕食>Cloud增量; Base 34%: 基本持平; Bull 38%: Cloud+AI持续抢份额
A11: --- Profitability ---
A12: Starting GM | C12: 0.597 | D12: 0.597 | E12: 0.597 | F12: =INDEX(C12:E12,$B$1) | G12: 59.7%：2025A实际毛利率
A13: Terminal GM | C13: 0.58 | D13: 0.615 | E13: 0.64 | F13: =INDEX(C13:E13,$B$1) | G13: Bear 58%: AI CapEx折旧压制; Base 61.5%: 每5年+1.8pp(参考2019-2025轨迹); Bull 64%: AI效率提升
A14: Starting Exp Ratio | C14: 0.277 | D14: 0.277 | E14: 0.277 | F14: =INDEX(C14:E14,$B$1) | G14: 27.7%：2025A实际费用率(RD+SGA占收入比)
A15: Terminal Exp Ratio | C15: 0.29 | D15: 0.26 | E15: 0.245 | F15: =INDEX(C15:E15,$B$1) | G15: Bear 29%: 竞争加剧需更多投入; Base 26%: 规模效应-1.7pp; Bull 24.5%: AI自动化降本
A16: Tax Rate | C16: 0.17 | D16: 0.15 | E16: 0.14 | F16: =INDEX(C16:E16,$B$1) | G16: 基于GOOGL历史有效税率14-17%，Bear取高、Bull取低
A17: --- Valuation ---
A18: Target PE | C18: 22 | D18: 27 | E18: 33 | F18: =INDEX(C18:E18,$B$1) | G18: Bear 22x: 向历史中位PE回归; Base 27x: 接近当前PE; Bull 33x: AI溢价维持
A19: Shares (M) (M) | C19: 5824 | D19: 5824 | E19: 5824 | F19: =INDEX(C19:E19,$B$1) | G19: 5824M：基于yfinance当前流通股数

Sheet Forecast
A1: Metric | B1: 2026E | C1: 2027E | D1: 2028E | E1: 2029E | F1: 2030E | G1: 2031E | H1: 2032E | I1: 2033E | J1: 2034E | K1: 2035E
A2: --- Revenue Build-up ---
A3: AIDC CapEx ($B) | B3: ='Assumptions'!$F$4*(1+'Assumptions'!$F$5) | C3: =B3*(1+'Assumptions'!$F$5) | D3: =C3*(1+'Assumptions'!$F$5) | E3: =D3*(1+'Assumptions'!$F$6) | F3: =E3*(1+'Assumptions'!$F$6) | G3: =F3*(1+'Assumptions'!$F$6) | H3: =G3*(1+'Assumptions'!$F$7) | I3: =H3*(1+'Assumptions'!$F$7) | J3: =I3*(1+'Assumptions'!$F$7) | K3: =J3*(1+'Assumptions'!$F$7)
A4: Addressable Mkt ($B) | B4: =B3*'Assumptions'!$F$8 | C4: =C3*'Assumptions'!$F$8 | D4: =D3*'Assumptions'!$F$8 | E4: =E3*'Assumptions'!$F$8 | F4: =F3*'Assumptions'!$F$8 | G4: =G3*'Assumptions'!$F$8 | H4: =H3*'Assumptions'!$F$8 | I4: =I3*'Assumptions'!$F$8 | ... K4: =K3*'Assumptions'!$F$8
A5: Market Share | B5: ='Assumptions'!$F$9+('Assumptions'!$F$10-'Assumptions'!$F$9)*0/9 | C5: ='Assumptions'!$F$9+('Assumptions'!$F$10-'Assumptions'!$F$9)*1/9 | D5: ='Assumptions'!$F$9+('Assumptions'!$F$10-'Assumptions'!$F$9)*2/9 | E5: ='Assumptions'!$F$9+('Assumptions'!$F$10-'Assumptions'!$F$9)*3/9 | F5: ='Assumptions'!$F$9+('Assumptions'!$F$10-'Assumptions'!$F$9)*4/9 | G5: ='Assumptions'!$F$9+('Assumptions'!$F$10-'Assumptions'!$F$9)*5/9 | H5: ='Assumptions'!$F$9+('Assumptions'!$F$10-'Assumptions'!$F$9)*6/9 | I5: ='Assumptions'!$F$9+('Assumptions'!$F$10-'Assumptions'!$F$9)*7/9 | J5: ='Assumptions'!$F$9+('Assumptions'!$F$10-'Assumptions'!$F$9)*8/9 | K5: ='Assumptions'!$F$9+('Assumptions'!$F$10-'Assumptions'!$F$9)*9/9
A6: Revenue ($B) | B6: =B4*B5 | C6: =C4*C5 | D6: =D4*D5 | E6: =E4*E5 | F6: =F4*F5 | G6: =G4*G5 | H6: =H4*H5 | I6: =I4*I5 | ... K6: =K4*K5
A7: Rev Growth | B7: =(B6*1000-402779)/402779 | C7: =(C6-B6)/B6 | D7: =(D6-C6)/C6 | E7: =(E6-D6)/D6 | F7: =(F6-E6)/E6 | G7: =(G6-F6)/F6 | H7: =(H6-G6)/G6 | I7: =(I6-H6)/H6 | J7: =(J6-I6)/I6 | K7: =(K6-J6)/J6
A9: --- Profit Build-up ---
A10: Gross Margin | B10: ='Assumptions'!$F$12+('Assumptions'!$F$13-'Assumptions'!$F$12)*0/9 | C10: ='Assumptions'!$F$12+('Assumptions'!$F$13-'Assumptions'!$F$12)*1/9 | D10: ='Assumptions'!$F$12+('Assumptions'!$F$13-'Assumptions'!$F$12)*2/9 | E10: ='Assumptions'!$F$12+('Assumptions'!$F$13-'Assumptions'!$F$12)*3/9 | F10: ='Assumptions'!$F$12+('Assumptions'!$F$13-'Assumptions'!$F$12)*4/9 | G10: ='Assumptions'!$F$12+('Assumptions'!$F$13-'Assumptions'!$F$12)*5/9 | H10: ='Assumptions'!$F$12+('Assumptions'!$F$13-'Assumptions'!$F$12)*6/9 | I10: ='Assumptions'!$F$12+('Assumptions'!$F$13-'Assumptions'!$F$12)*7/9 | J10: ='Assumptions'!$F$12+('Assumptions'!$F$13-'Assumptions'!$F$12)*8/9 | K10: ='Assumptions'!$F$12+('Assumptions'!$F$13-'Assumptions'!$F$12)*9/9
A11: Gross Profit ($B) | B11: =B6*B10 | C11: =C6*C10 | D11: =D6*D10 | E11: =E6*E10 | F11: =F6*F10 | G11: =G6*G10 | H11: =H6*H10 | I11: =I6*I10 | ... K11: =K6*K10
A12: Expense Ratio | B12: ='Assumptions'!$F$14+('Assumptions'!$F$15-'Assumptions'!$F$14)*0/9 | C12: ='Assumptions'!$F$14+('Assumptions'!$F$15-'Assumptions'!$F$14)*1/9 | D12: ='Assumptions'!$F$14+('Assumptions'!$F$15-'Assumptions'!$F$14)*2/9 | E12: ='Assumptions'!$F$14+('Assumptions'!$F$15-'Assumptions'!$F$14)*3/9 | F12: ='Assumptions'!$F$14+('Assumptions'!$F$15-'Assumptions'!$F$14)*4/9 | G12: ='Assumptions'!$F$14+('Assumptions'!$F$15-'Assumptions'!$F$14)*5/9 | H12: ='Assumptions'!$F$14+('Assumptions'!$F$15-'Assumptions'!$F$14)*6/9 | I12: ='Assumptions'!$F$14+('Assumptions'!$F$15-'Assumptions'!$F$14)*7/9 | J12: ='Assumptions'!$F$14+('Assumptions'!$F$15-'Assumptions'!$F$14)*8/9 | K12: ='Assumptions'!$F$14+('Assumptions'!$F$15-'Assumptions'!$F$14)*9/9
A13: OpEx ($B) | B13: =B6*B12 | C13: =C6*C12 | D13: =D6*D12 | E13: =E6*E12 | F13: =F6*F12 | G13: =G6*G12 | H13: =H6*H12 | I13: =I6*I12 | ... K13: =K6*K12
A14: EBIT ($B) | B14: =B11-B13 | C14: =C11-C13 | D14: =D11-D13 | E14: =E11-E13 | F14: =F11-F13 | G14: =G11-G13 | H14: =H11-H13 | I14: =I11-I13 | ... K14: =K11-K13
A15: Tax Rate | B15: ='Assumptions'!$F$16 | C15: ='Assumptions'!$F$16 | D15: ='Assumptions'!$F$16 | E15: ='Assumptions'!$F$16 | F15: ='Assumptions'!$F$16 | G15: ='Assumptions'!$F$16 | H15: ='Assumptions'!$F$16 | I15: ='Assumptions'!$F$16 | ... K15: ='Assumptions'!$F$16
A16: Net Income ($B) | B16: =B14*(1-B15) | C16: =C14*(1-C15) | D16: =D14*(1-D15) | E16: =E14*(1-E15) | F16: =F14*(1-F15) | G16: =G14*(1-G15) | H16: =H14*(1-H15) | I16: =I14*(1-I15) | ... K16: =K14*(1-K15)
A18: --- Valuation ---
A19: Target PE | B19: ='Assumptions'!$F$18 | C19: ='Assumptions'!$F$18 | D19: ='Assumptions'!$F$18 | E19: ='Assumptions'!$F$18 | F19: ='Assumptions'!$F$18 | G19: ='Assumptions'!$F$18 | H19: ='Assumptions'!$F$18 | I19: ='Assumptions'!$F$18 | ... K19: ='Assumptions'!$F$18
A20: Implied Mkt Cap ($B) | B20: =B16*B19 | C20: =C16*C19 | D20: =D16*D19 | E20: =E16*E19 | F20: =F16*F19 | G20: =G16*G19 | H20: =H16*H19 | I20: =I16*I19 | ... K20: =K16*K19
A21: Shares (M) | B21: ='Assumptions'!$F$19 | C21: ='Assumptions'!$F$19 | D21: ='Assumptions'!$F$19 | E21: ='Assumptions'!$F$19 | F21: ='Assumptions'!$F$19 | G21: ='Assumptions'!$F$19 | H21: ='Assumptions'!$F$19 | I21: ='Assumptions'!$F$19 | ... K21: ='Assumptions'!$F$19
A22: Implied Price ($) | B22: =B20*1000/B21 | C22: =C20*1000/C21 | D22: =D20*1000/D21 | E22: =E20*1000/E21 | F22: =F20*1000/F21 | G22: =G20*1000/G21 | H22: =H20*1000/H21 | I22: =I20*1000/I21 | ... K22: =K20*1000/K21
A23: vs Current Premium | B23: =(B22-387.35)/387.35 | C23: =(C22-387.35)/387.35 | D23: =(D22-387.35)/387.35 | E23: =(E22-387.35)/387.35 | F23: =(F22-387.35)/387.35 | G23: =(G22-387.35)/387.35 | H23: =(H22-387.35)/387.35 | I23: =(I22-387.35)/387.35 | ... K23: =(K22-387.35)/387.35

Sheet Sanity Checks
A1: Metric | B1: Bear | C1: Base | D1: Bull | E1: Status
A2: [BEAR] 收入增速衰减 | B2: ✓ | E2: ✓ 通过
A3: [BEAR] 毛利率范围 | B3: ✓ | E3: ✓ 通过
A4: [BEAR] EBIT margin 合理 | B4: ✓ | E4: ✓ 通过
A5: [BASE] 收入增速衰减 | C5: ✓ | E5: ✓ 通过
A6: [BASE] 毛利率范围 | C6: ✓ | E6: ✓ 通过
A7: [BASE] EBIT margin 合理 | C7: ✓ | E7: ✓ 通过
A8: [BULL] 收入增速衰减 | D8: ✓ | E8: ✓ 通过
A9: [BULL] 毛利率范围 | D9: ✓ | E9: ✓ 通过
A10: [BULL] EBIT margin 合理 | D10: ✓ | E10: ✓ 通过
A11: 终年收入排序 Bull>Base>Bear | B11: $671B | C11: $1016B | D11: $1648B | E11: ✓ 通过
A12: 终年净利排序 Bull>Base>Bear | B12: $162B | C12: $306B | D12: $560B | E12: ✓ 通过
A13: 情景差距合理性 (B/B=133%, Bu/B=123%) | E13: ✓ 通过
A14: Base CAGR (9.7%) vs MSFT历史 (~12%) | C14: 9.7% | E14: ✓ 合理
